click/__init__.py
click/_compat.py
click/_termui_impl.py
click/_textwrap.py
click/_winconsole.py
click/core.py
click/decorators.py
click/exceptions.py
click/formatting.py
click/globals.py
click/parser.py
click/py.typed
click/shell_completion.py
click/termui.py
click/testing.py
click/types.py
click/utils.py
click-8.1.5.dist-info/LICENSE.rst
click-8.1.5.dist-info/METADATA
click-8.1.5.dist-info/WHEEL
click-8.1.5.dist-info/top_level.txt
click-8.1.5.dist-info/RECORD
