Metadata-Version: 2.1
Name: click
Version: 8.1.5
Summary: Composable command line interface toolkit
Home-page: https://palletsprojects.com/p/click/
Maintainer: Pallets
Maintainer-email: contact@palletsprojects.com
License: BSD-3-Clause
Project-URL: Donate, https://palletsprojects.com/donate
Project-URL: Documentation, https://click.palletsprojects.com/
Project-URL: Changes, https://click.palletsprojects.com/changes/
Project-URL: Source Code, https://github.com/pallets/click/
Project-URL: Issue Tracker, https://github.com/pallets/click/issues/
Project-URL: Chat, https://discord.gg/pallets
Classifier: Development Status :: 5 - Production/Stable
Classifier: Intended Audience :: Developers
Classifier: License :: OSI Approved :: BSD License
Classifier: Operating System :: OS Independent
Classifier: Programming Language :: Python
Requires-Python: >=3.7
License-File: LICENSE.rst
